pybpa/__init__.py
pybpa/nrscp.py
pybpa/base/__init__.py
pybpa/base/bpa_annotation.py
pybpa/base/bpa_base.py
pybpa/base/bpa_str.py
pybpa/base/bpa_uid.py
pybpa/dat/__init__.py
pybpa/dat/bpa_dat.py
pybpa/dat/bpa_dat_before_data.py
pybpa/dat/bpa_dat_data.py
pybpa/lsd/__init__.py
pybpa/lsd/nrscp_lsd.py
pybpa/organize/__init__.py
pybpa/organize/file_organize.py
pybpa/organize/organizer.py
pybpa/swi/__init__.py
pybpa/swi/bpa_swi.py
pybpa/swi/bpa_swi_control_and_model.py
pybpa/swi/bpa_swi_output.py
pybpa/task/__init__.py
pybpa/task/file_system_task.py
pybpa/task/gen_new_folders.py
pybpa/task/n-012randomPQ.py
pybpa/task/pid_supervisor.py
pybpa/utils/__init__.py
pybpa/utils/file_operation.py
pybpa/utils/utils.py
pybpa-0.10.4.dist-info/LICENSE
pybpa-0.10.4.dist-info/METADATA
pybpa-0.10.4.dist-info/WHEEL
pybpa-0.10.4.dist-info/top_level.txt
pybpa-0.10.4.dist-info/RECORD
