Metadata-Version: 2.1
Name: pybpa
Version: 0.10.4
Summary: A BPA file(dat/swi) resolver. The author wish to thank ZHU Siting for her contribution to the project. Her work has advanced the project's resolution of real industrial systems.
Home-page: https://github.com/Kayya886/pybpa
Author: Milk
Author-email: Milk <jeremychenlk@qq.com>
Project-URL: Homepage, https://github.com/Kayya886/pybpa
Project-URL: Bug Tracker, https://github.com/Kayya886/pybpa/issues
Classifier: Programming Language :: Python :: 3
Classifier: Operating System :: OS Independent
Requires-Python: >=3.6
License-File: LICENSE
